LICENSE.txt
README.md
Setup.py
setup.cfg
setup.py
ColorText/ColorText.py
ColorText/__init__.py
ColorText.egg-info/PKG-INFO
ColorText.egg-info/SOURCES.txt
ColorText.egg-info/dependency_links.txt
ColorText.egg-info/top_level.txt