Metadata-Version: 1.0
Name: ColorText
Version: 1.0.0
Summary: Programa simples de mudança de cor de texto
Home-page: https://github.com/JonatasMSS/ColorText
Author: Jonatas Miguel
Author-email: jonatas.miguelss@gmail.com
License: UNKNOWN
Keywords: Mudar cor texto
Platform: UNKNOWN
